MANIFEST.in
README.rst
requirements-test.txt
requirements.txt
setup.py
saexttype/__init__.py
saexttype.egg-info/PKG-INFO
saexttype.egg-info/SOURCES.txt
saexttype.egg-info/dependency_links.txt
saexttype.egg-info/not-zip-safe
saexttype.egg-info/pbr.json
saexttype.egg-info/requires.txt
saexttype.egg-info/top_level.txt